resonate/__init__.py
resonate/abacus_plot.py
resonate/att_formatter.py
resonate/bubble_plot.py
resonate/cohorts.py
resonate/compress.py
resonate/filters.py
resonate/interval_data_tool.py
resonate/receiver_efficiency.py
resonate/residence_index.py
resonate/uniqueid.py
resonate/visual_timeline.py
resonate/library/__init__.py
resonate/library/exceptions.py
resonATe-1.0.8.dist-info/LICENSE
resonATe-1.0.8.dist-info/METADATA
resonATe-1.0.8.dist-info/WHEEL
resonATe-1.0.8.dist-info/top_level.txt
resonATe-1.0.8.dist-info/RECORD
