Metadata-Version: 2.1
Name: resonATe
Version: 1.0.8
Summary: resonate data analysis package
Home-page: https://gitlab.oceantrack.org/otndc/resonate
Author: Alex Nunes
Author-email: anunes@dal.ca
License: GPLv2
Download-URL: https://gitlab.oceantrack.org/otndc/resonate
Platform: UNKNOWN
Classifier: Natural Language :: English
Classifier: Operating System :: OS Independent
Classifier: Programming Language :: Python
Classifier: Programming Language :: Python :: 2.7
Classifier: Programming Language :: Python :: 3.5
Classifier: Programming Language :: Python :: 3.6
